README.md
setup.py
dsbox_graphs/__init__.py
dsbox_graphs/config_.py
dsbox_graphs/gcn_mixhop.py
dsbox_graphs/gcn_utils.py
dsbox_graphs/sdne.py
dsbox_graphs.egg-info/PKG-INFO
dsbox_graphs.egg-info/SOURCES.txt
dsbox_graphs.egg-info/dependency_links.txt
dsbox_graphs.egg-info/entry_points.txt
dsbox_graphs.egg-info/requires.txt
dsbox_graphs.egg-info/top_level.txt
dsbox_graphs/GEM/__init__.py
dsbox_graphs/GEM/setup.py
dsbox_graphs/GEM/gem/__init__.py
dsbox_graphs/GEM/gem/c_ext/__init__.py
dsbox_graphs/GEM/gem/embedding/__init__.py
dsbox_graphs/GEM/gem/embedding/gf.py
dsbox_graphs/GEM/gem/embedding/hope.py
dsbox_graphs/GEM/gem/embedding/lap.py
dsbox_graphs/GEM/gem/embedding/lle.py
dsbox_graphs/GEM/gem/embedding/node2vec.py
dsbox_graphs/GEM/gem/embedding/sdne.py
dsbox_graphs/GEM/gem/embedding/sdne_utils.py
dsbox_graphs/GEM/gem/embedding/static_graph_embedding.py
dsbox_graphs/GEM/gem/evaluation/__init__.py
dsbox_graphs/GEM/gem/evaluation/evaluate_graph_reconstruction.py
dsbox_graphs/GEM/gem/evaluation/evaluate_link_prediction.py
dsbox_graphs/GEM/gem/evaluation/evaluate_node_classification.py
dsbox_graphs/GEM/gem/evaluation/metrics.py
dsbox_graphs/GEM/gem/evaluation/visualize_embedding.py
dsbox_graphs/GEM/gem/utils/__init__.py
dsbox_graphs/GEM/gem/utils/embed_util.py
dsbox_graphs/GEM/gem/utils/evaluation_util.py
dsbox_graphs/GEM/gem/utils/graph_util.py
dsbox_graphs/GEM/gem/utils/plot_util.py